.gitignore
AUTHORS
LICENSE
README.md
setup.py
django_seo_i18n.egg-info/PKG-INFO
django_seo_i18n.egg-info/SOURCES.txt
django_seo_i18n.egg-info/dependency_links.txt
django_seo_i18n.egg-info/requires.txt
django_seo_i18n.egg-info/top_level.txt
seo_i18n/__init__.py
seo_i18n/admin.py
seo_i18n/forms.py
seo_i18n/models.py
seo_i18n/querysets.py
seo_i18n/migrations/0001_initial.py
seo_i18n/migrations/0002_seo_robots.py
seo_i18n/migrations/0003_auto_20201104_1150.py
seo_i18n/migrations/0004_auto_20201104_1203.py
seo_i18n/migrations/0005_auto_20201104_1205.py
seo_i18n/migrations/0006_auto_20201104_1213.py
seo_i18n/migrations/0007_auto_20201104_1254.py
seo_i18n/migrations/0008_seo_image.py
seo_i18n/migrations/0009_auto_20201105_1337.py
seo_i18n/migrations/__init__.py
seo_i18n/templatetags/__init__.py
seo_i18n/templatetags/seo_i18n.py